{
    "formatVersion": 1,
    "libraries": [
        {
            "downloads": {
                "artifact": {
                    "sha1": "a81144a13158a3ef161592665d61e1557e4cbdb1",
                    "size": 461630,
                    "url": "https://maven.fabricmc.net/net/fabricmc/intermediary/21w37a/intermediary-21w37a.jar"
                }
            },
            "name": "net.fabricmc:intermediary:21w37a"
        }
    ],
    "name": "Intermediary Mappings",
    "order": 11,
    "releaseTime": "2021-09-16T20:59:12+00:00",
    "requires": [
        {
            "equals": "21w37a",
            "uid": "net.minecraft"
        }
    ],
    "type": "release",
    "uid": "net.fabricmc.intermediary",
    "version": "21w37a",
    "volatile": true
}