{
    "formatVersion": 1,
    "libraries": [
        {
            "downloads": {
                "artifact": {
                    "sha1": "1c34fa15ad4b3e12673befc07aeb3342ca4f8d70",
                    "size": 531615,
                    "url": "https://maven.fabricmc.net/net/fabricmc/intermediary/22w44a/intermediary-22w44a.jar"
                }
            },
            "name": "net.fabricmc:intermediary:22w44a"
        }
    ],
    "name": "Intermediary Mappings",
    "order": 11,
    "releaseTime": "2022-11-02T14:59:10+00:00",
    "requires": [
        {
            "equals": "22w44a",
            "uid": "net.minecraft"
        }
    ],
    "type": "release",
    "uid": "net.fabricmc.intermediary",
    "version": "22w44a",
    "volatile": true
}